ndarray_msg_utils/__init__.py
ndarray_msg_utils/conversion.py
ndarray_msg_utils/py.typed
ndarray_msg_utils/torch.py
ndarray_msg_utils/utils.py
ros2_ndarray_msg_utils-0.2.0.dist-info/METADATA
ros2_ndarray_msg_utils-0.2.0.dist-info/WHEEL
ros2_ndarray_msg_utils-0.2.0.dist-info/licenses/LICENSE
ros2_ndarray_msg_utils-0.2.0.dist-info/RECORD
