Metadata-Version: 2.4
Name: ros2-ndarray-msg-utils
Version: 0.2.0
Summary: A ROS2 package for transmitting NumPy ndarrays between ROS2 nodes.
Project-URL: Repository, https://github.com/Geson-anko/numpy_ndarray_msgs
Project-URL: Issues, https://github.com/Geson-anko/numpy_ndarray_msgs/issues
Author-email: Geson-anko <59220704+Geson-anko@users.noreply.github.com>
License-File: LICENSE
Keywords: AI,ML,Machine Learning,Message,Numpy,PyTorch,ROS,ROS2,Torch
Classifier: Development Status :: 4 - Beta
Classifier: Intended Audience :: Developers
Classifier: Intended Audience :: Science/Research
Classifier: License :: OSI Approved :: MIT License
Classifier: Natural Language :: English
Classifier: Natural Language :: Japanese
Classifier: Programming Language :: Python :: 3
Classifier: Programming Language :: Python :: 3.10
Classifier: Programming Language :: Python :: 3.12
Requires-Python: >=3.10
Requires-Dist: numpy>=1.21.5
Provides-Extra: torch
Requires-Dist: torch>=2.0.0; extra == 'torch'
